LICENSE
README.md
setup.py
promcse/__init__.py
promcse/models.py
promcse/tool.py
promcse/trainers.py
promcse.egg-info/PKG-INFO
promcse.egg-info/SOURCES.txt
promcse.egg-info/dependency_links.txt
promcse.egg-info/requires.txt
promcse.egg-info/top_level.txt