Metadata-Version: 2.1
Name: promcse
Version: 0.0.2
Summary: A sentence embedding tool based on PromCSE
Home-page: https://github.com/YJiangcm/PromCSE
Download-URL: https://github.com/YJiangcm/PromCSE/archive/refs/tags/0.0.2.tar.gz
Author: Yuxin Jiang
Author-email: yjiangcm@connect.ust.hk
License: MIT
Keywords: sentence,embedding,promcse,nlp,prompt
License-File: LICENSE
